{
  "url": "https://api.github.com/repos/BurntSushi/ripgrep/releases/254873528",
  "assets_url": "https://api.github.com/repos/BurntSushi/ripgrep/releases/254873528/assets",
  "upload_url": "https://uploads.github.com/repos/BurntSushi/ripgrep/releases/254873528/assets{?name,label}",
  "html_url": "https://github.com/BurntSushi/ripgrep/releases/tag/15.0.0",
  "id": 254873528,
  "author": {
    "login": "github-actions[bot]",
    "id": 41898282,
    "node_id": "MDM6Qm90NDE4OTgyODI=",
    "avatar_url": "https://avatars.githubusercontent.com/in/15368?v=4",
    "gravatar_id": "",
    "url": "https://api.github.com/users/github-actions%5Bbot%5D",
    "html_url": "https://github.com/apps/github-actions",
    "followers_url": "https://api.github.com/users/github-actions%5Bbot%5D/followers",
    "following_url": "https://api.github.com/users/github-actions%5Bbot%5D/following{/other_user}",
    "gists_url": "https://api.github.com/users/github-actions%5Bbot%5D/gists{/gist_id}",
    "starred_url": "https://api.github.com/users/github-actions%5Bbot%5D/starred{/owner}{/repo}",
    "subscriptions_url": "https://api.github.com/users/github-actions%5Bbot%5D/subscriptions",
    "organizations_url": "https://api.github.com/users/github-actions%5Bbot%5D/orgs",
    "repos_url": "https://api.github.com/users/github-actions%5Bbot%5D/repos",
    "events_url": "https://api.github.com/users/github-actions%5Bbot%5D/events{/privacy}",
    "received_events_url": "https://api.github.com/users/github-actions%5Bbot%5D/received_events",
    "type": "Bot",
    "user_view_type": "public",
    "site_admin": false
  },
  "node_id": "RE_kwDOAzJbyc4PMQ-4",
  "tag_name": "15.0.0",
  "target_commitish": "master",
  "name": "15.0.0",
  "draft": false,
  "immutable": false,
  "prerelease": false,
  "created_at": "2025-10-16T03:08:06Z",
  "updated_at": "2025-10-16T03:26:46Z",
  "published_at": "2025-10-16T03:17:57Z",
  "assets": [
    {
      "url": "https://api.github.com/repos/BurntSushi/ripgrep/releases/assets/304880546",
      "id": 304880546,
      "node_id": "RA_kwDOAzJbyc4SLBui",
      "name": "ripgrep-15.0.0-aarch64-apple-darwin.tar.gz",
      "label": "",
      "uploader": {
        "login": "github-actions[bot]",
        "id": 41898282,
        "node_id": "MDM6Qm90NDE4OTgyODI=",
        "avatar_url": "https://avatars.githubusercontent.com/in/15368?v=4",
        "gravatar_id": "",
        "url": "https://api.github.com/users/github-actions%5Bbot%5D",
        "html_url": "https://github.com/apps/github-actions",
        "followers_url": "https://api.github.com/users/github-actions%5Bbot%5D/followers",
        "following_url": "https://api.github.com/users/github-actions%5Bbot%5D/following{/other_user}",
        "gists_url": "https://api.github.com/users/github-actions%5Bbot%5D/gists{/gist_id}",
        "starred_url": "https://api.github.com/users/github-actions%5Bbot%5D/starred{/owner}{/repo}",
        "subscriptions_url": "https://api.github.com/users/github-actions%5Bbot%5D/subscriptions",
        "organizations_url": "https://api.github.com/users/github-actions%5Bbot%5D/orgs",
        "repos_url": "https://api.github.com/users/github-actions%5Bbot%5D/repos",
        "events_url": "https://api.github.com/users/github-actions%5Bbot%5D/events{/privacy}",
        "received_events_url": "https://api.github.com/users/github-actions%5Bbot%5D/received_events",
        "type": "Bot",
        "user_view_type": "public",
        "site_admin": false
      },
      "content_type": "application/x-gtar",
      "state": "uploaded",
      "size": 1775660,
      "digest": "sha256:98bb2e61e7277ba0ea72d2ae2592497fd8d2940934a16b122448d302a6637e3b",
      "download_count": 8072,
      "created_at": "2025-10-16T03:18:30Z",
      "updated_at": "2025-10-16T03:18:31Z",
      "browser_download_url": "https://github.com/BurntSushi/ripgrep/releases/download/15.0.0/ripgrep-15.0.0-aarch64-apple-darwin.tar.gz"
    },
    {
      "url": "https://api.github.com/repos/BurntSushi/ripgrep/releases/assets/304880545",
      "id": 304880545,
      "node_id": "RA_kwDOAzJbyc4SLBuh",
      "name": "ripgrep-15.0.0-aarch64-apple-darwin.tar.gz.sha256",
      "label": "",
      "uploader": {
        "login": "github-actions[bot]",
        "id": 41898282,
        "node_id": "MDM6Qm90NDE4OTgyODI=",
        "avatar_url": "https://avatars.githubusercontent.com/in/15368?v=4",
        "gravatar_id": "",
        "url": "https://api.github.com/users/github-actions%5Bbot%5D",
        "html_url": "https://github.com/apps/github-actions",
        "followers_url": "https://api.github.com/users/github-actions%5Bbot%5D/followers",
        "following_url": "https://api.github.com/users/github-actions%5Bbot%5D/following{/other_user}",
        "gists_url": "https://api.github.com/users/github-actions%5Bbot%5D/gists{/gist_id}",
        "starred_url": "https://api.github.com/users/github-actions%5Bbot%5D/starred{/owner}{/repo}",
        "subscriptions_url": "https://api.github.com/users/github-actions%5Bbot%5D/subscriptions",
        "organizations_url": "https://api.github.com/users/github-actions%5Bbot%5D/orgs",
        "repos_url": "https://api.github.com/users/github-actions%5Bbot%5D/repos",
        "events_url": "https://api.github.com/users/github-actions%5Bbot%5D/events{/privacy}",
        "received_events_url": "https://api.github.com/users/github-actions%5Bbot%5D/received_events",
        "type": "Bot",
        "user_view_type": "public",
        "site_admin": false
      },
      "content_type": "application/octet-stream",
      "state": "uploaded",
      "size": 109,
      "digest": "sha256:260782b063db2b037b69d6bdd8e5341e966ce5954ed4b6ecc10d873f23a1a59b",
      "download_count": 1622,
      "created_at": "2025-10-16T03:18:30Z",
      "updated_at": "2025-10-16T03:18:31Z",
      "browser_download_url": "https://github.com/BurntSushi/ripgrep/releases/download/15.0.0/ripgrep-15.0.0-aarch64-apple-darwin.tar.gz.sha256"
    },
    {
      "url": "https://api.github.com/repos/BurntSushi/ripgrep/releases/assets/304881041",
      "id": 304881041,
      "node_id": "RA_kwDOAzJbyc4SLB2R",
      "name": "ripgrep-15.0.0-aarch64-pc-windows-msvc.zip",
      "label": "",
      "uploader": {
        "login": "github-actions[bot]",
        "id": 41898282,
        "node_id": "MDM6Qm90NDE4OTgyODI=",
        "avatar_url": "https://avatars.githubusercontent.com/in/15368?v=4",
        "gravatar_id": "",
        "url": "https://api.github.com/users/github-actions%5Bbot%5D",
        "html_url": "https://github.com/apps/github-actions",
        "followers_url": "https://api.github.com/users/github-actions%5Bbot%5D/followers",
        "following_url": "https://api.github.com/users/github-actions%5Bbot%5D/following{/other_user}",
        "gists_url": "https://api.github.com/users/github-actions%5Bbot%5D/gists{/gist_id}",
        "starred_url": "https://api.github.com/users/github-actions%5Bbot%5D/starred{/owner}{/repo}",
        "subscriptions_url": "https://api.github.com/users/github-actions%5Bbot%5D/subscriptions",
        "organizations_url": "https://api.github.com/users/github-actions%5Bbot%5D/orgs",
        "repos_url": "https://api.github.com/users/github-actions%5Bbot%5D/repos",
        "events_url": "https://api.github.com/users/github-actions%5Bbot%5D/events{/privacy}",
        "received_events_url": "https://api.github.com/users/github-actions%5Bbot%5D/received_events",
        "type": "Bot",
        "user_view_type": "public",
        "site_admin": false
      },
      "content_type": "application/zip",
      "state": "uploaded",
      "size": 1673744,
      "digest": "sha256:572709c8770cb7f9385d725cb06d2bcd9537ec24d4dd17b1be1d65a876f8b591",
      "download_count": 1814,
      "created_at": "2025-10-16T03:20:45Z",
      "updated_at": "2025-10-16T03:20:46Z",
      "browser_download_url": "https://github.com/BurntSushi/ripgrep/releases/download/15.0.0/ripgrep-15.0.0-aarch64-pc-windows-msvc.zip"
    },
    {
      "url": "https://api.github.com/repos/BurntSushi/ripgrep/releases/assets/304881040",
      "id": 304881040,
      "node_id": "RA_kwDOAzJbyc4SLB2Q",
      "name": "ripgrep-15.0.0-aarch64-pc-windows-msvc.zip.sha256",
      "label": "",
      "uploader": {
        "login": "github-actions[bot]",
        "id": 41898282,
        "node_id": "MDM6Qm90NDE4OTgyODI=",
        "avatar_url": "https://avatars.githubusercontent.com/in/15368?v=4",
        "gravatar_id": "",
        "url": "https://api.github.com/users/github-actions%5Bbot%5D",
        "html_url": "https://github.com/apps/github-actions",
        "followers_url": "https://api.github.com/users/github-actions%5Bbot%5D/followers",
        "following_url": "https://api.github.com/users/github-actions%5Bbot%5D/following{/other_user}",
        "gists_url": "https://api.github.com/users/github-actions%5Bbot%5D/gists{/gist_id}",
        "starred_url": "https://api.github.com/users/github-actions%5Bbot%5D/starred{/owner}{/repo}",
        "subscriptions_url": "https://api.github.com/users/github-actions%5Bbot%5D/subscriptions",
        "organizations_url": "https://api.github.com/users/github-actions%5Bbot%5D/orgs",
        "repos_url": "https://api.github.com/users/github-actions%5Bbot%5D/repos",
        "events_url": "https://api.github.com/users/github-actions%5Bbot%5D/events{/privacy}",
        "received_events_url": "https://api.github.com/users/github-actions%5Bbot%5D/received_events",
        "type": "Bot",
        "user_view_type": "public",
        "site_admin": false
      },
      "content_type": "application/octet-stream",
      "state": "uploaded",
      "size": 179,
      "digest": "sha256:9c5e0524b9a915fadf56ae8f22af1292af24b86733e52df125f8ac08cbdfb03f",
      "download_count": 1191,
      "created_at": "2025-10-16T03:20:45Z",
      "updated_at": "2025-10-16T03:20:45Z",
      "browser_download_url": "https://github.com/BurntSushi/ripgrep/releases/download/15.0.0/ripgrep-15.0.0-aarch64-pc-windows-msvc.zip.sha256"
    },
    {
      "url": "https://api.github.com/repos/BurntSushi/ripgrep/releases/assets/304880791",
      "id": 304880791,
      "node_id": "RA_kwDOAzJbyc4SLByX",
      "name": "ripgrep-15.0.0-aarch64-unknown-linux-gnu.tar.gz",
      "label": "",
      "uploader": {
        "login": "github-actions[bot]",
        "id": 41898282,
        "node_id": "MDM6Qm90NDE4OTgyODI=",
        "avatar_url": "https://avatars.githubusercontent.com/in/15368?v=4",
        "gravatar_id": "",
        "url": "https://api.github.com/users/github-actions%5Bbot%5D",
        "html_url": "https://github.com/apps/github-actions",
        "followers_url": "https://api.github.com/users/github-actions%5Bbot%5D/followers",
        "following_url": "https://api.github.com/users/github-actions%5Bbot%5D/following{/other_user}",
        "gists_url": "https://api.github.com/users/github-actions%5Bbot%5D/gists{/gist_id}",
        "starred_url": "https://api.github.com/users/github-actions%5Bbot%5D/starred{/owner}{/repo}",
        "subscriptions_url": "https://api.github.com/users/github-actions%5Bbot%5D/subscriptions",
        "organizations_url": "https://api.github.com/users/github-actions%5Bbot%5D/orgs",
        "repos_url": "https://api.github.com/users/github-actions%5Bbot%5D/repos",
        "events_url": "https://api.github.com/users/github-actions%5Bbot%5D/events{/privacy}",
        "received_events_url": "https://api.github.com/users/github-actions%5Bbot%5D/received_events",
        "type": "Bot",
        "user_view_type": "public",
        "site_admin": false
      },
      "content_type": "application/x-gtar",
      "state": "uploaded",
      "size": 1864542,
      "digest": "sha256:15f8cc2fab12d88491c54d49f38589922a9d6a7353c29b0a0856727bcdf80754",
      "download_count": 6844,
      "created_at": "2025-10-16T03:19:44Z",
      "updated_at": "2025-10-16T03:19:44Z",
      "browser_download_url": "https://github.com/BurntSushi/ripgrep/releases/download/15.0.0/ripgrep-15.0.0-aarch64-unknown-linux-gnu.tar.gz"
    },
    {
      "url": "https://api.github.com/repos/BurntSushi/ripgrep/releases/assets/304880790",
      "id": 304880790,
      "node_id": "RA_kwDOAzJbyc4SLByW",
      "name": "ripgrep-15.0.0-aarch64-unknown-linux-gnu.tar.gz.sha256",
      "label": "",
      "uploader": {
        "login": "github-actions[bot]",
        "id": 41898282,
        "node_id": "MDM6Qm90NDE4OTgyODI=",
        "avatar_url": "https://avatars.githubusercontent.com/in/15368?v=4",
        "gravatar_id": "",
        "url": "https://api.github.com/users/github-actions%5Bbot%5D",
        "html_url": "https://github.com/apps/github-actions",
        "followers_url": "https://api.github.com/users/github-actions%5Bbot%5D/followers",
        "following_url": "https://api.github.com/users/github-actions%5Bbot%5D/following{/other_user}",
        "gists_url": "https://api.github.com/users/github-actions%5Bbot%5D/gists{/gist_id}",
        "starred_url": "https://api.github.com/users/github-actions%5Bbot%5D/starred{/owner}{/repo}",
        "subscriptions_url": "https://api.github.com/users/github-actions%5Bbot%5D/subscriptions",
        "organizations_url": "https://api.github.com/users/github-actions%5Bbot%5D/orgs",
        "repos_url": "https://api.github.com/users/github-actions%5Bbot%5D/repos",
        "events_url": "https://api.github.com/users/github-actions%5Bbot%5D/events{/privacy}",
        "received_events_url": "https://api.github.com/users/github-actions%5Bbot%5D/received_events",
        "type": "Bot",
        "user_view_type": "public",
        "site_admin": false
      },
      "content_type": "application/octet-stream",
      "state": "uploaded",
      "size": 114,
      "digest": "sha256:c970194b9d4958bb1a586c9f4cc9451bad5f76fcd6153ff1b6dd2def42e8eec9",
      "download_count": 1352,
      "created_at": "2025-10-16T03:19:44Z",
      "updated_at": "2025-10-16T03:19:44Z",
      "browser_download_url": "https://github.com/BurntSushi/ripgrep/releases/download/15.0.0/ripgrep-15.0.0-aarch64-unknown-linux-gnu.tar.gz.sha256"
    },
    {
      "url": "https://api.github.com/repos/BurntSushi/ripgrep/releases/assets/304881032",
      "id": 304881032,
      "node_id": "RA_kwDOAzJbyc4SLB2I",
      "name": "ripgrep-15.0.0-armv7-unknown-linux-gnueabihf.tar.gz",
      "label": "",
      "uploader": {
        "login": "github-actions[bot]",
        "id": 41898282,
        "node_id": "MDM6Qm90NDE4OTgyODI=",
        "avatar_url": "https://avatars.githubusercontent.com/in/15368?v=4",
        "gravatar_id": "",
        "url": "https://api.github.com/users/github-actions%5Bbot%5D",
        "html_url": "https://github.com/apps/github-actions",
        "followers_url": "https://api.github.com/users/github-actions%5Bbot%5D/followers",
        "following_url": "https://api.github.com/users/github-actions%5Bbot%5D/following{/other_user}",
        "gists_url": "https://api.github.com/users/github-actions%5Bbot%5D/gists{/gist_id}",
        "starred_url": "https://api.github.com/users/github-actions%5Bbot%5D/starred{/owner}{/repo}",
        "subscriptions_url": "https://api.github.com/users/github-actions%5Bbot%5D/subscriptions",
        "organizations_url": "https://api.github.com/users/github-actions%5Bbot%5D/orgs",
        "repos_url": "https://api.github.com/users/github-actions%5Bbot%5D/repos",
        "events_url": "https://api.github.com/users/github-actions%5Bbot%5D/events{/privacy}",
        "received_events_url": "https://api.github.com/users/github-actions%5Bbot%5D/received_events",
        "type": "Bot",
        "user_view_type": "public",
        "site_admin": false
      },
      "content_type": "application/x-gtar",
      "state": "uploaded",
      "size": 1843702,
      "digest": "sha256:126182ae4c85892546aaabc406f2f9271c609ec7fd6603055783456b339a8f9e",
      "download_count": 1205,
      "created_at": "2025-10-16T03:20:43Z",
      "updated_at": "2025-10-16T03:20:43Z",
      "browser_download_url": "https://github.com/BurntSushi/ripgrep/releases/download/15.0.0/ripgrep-15.0.0-armv7-unknown-linux-gnueabihf.tar.gz"
    },
    {
      "url": "https://api.github.com/repos/BurntSushi/ripgrep/releases/assets/304881031",
      "id": 304881031,
      "node_id": "RA_kwDOAzJbyc4SLB2H",
      "name": "ripgrep-15.0.0-armv7-unknown-linux-gnueabihf.tar.gz.sha256",
      "label": "",
      "uploader": {
        "login": "github-actions[bot]",
        "id": 41898282,
        "node_id": "MDM6Qm90NDE4OTgyODI=",
        "avatar_url": "https://avatars.githubusercontent.com/in/15368?v=4",
        "gravatar_id": "",
        "url": "https://api.github.com/users/github-actions%5Bbot%5D",
        "html_url": "https://github.com/apps/github-actions",
        "followers_url": "https://api.github.com/users/github-actions%5Bbot%5D/followers",
        "following_url": "https://api.github.com/users/github-actions%5Bbot%5D/following{/other_user}",
        "gists_url": "https://api.github.com/users/github-actions%5Bbot%5D/gists{/gist_id}",
        "starred_url": "https://api.github.com/users/github-actions%5Bbot%5D/starred{/owner}{/repo}",
        "subscriptions_url": "https://api.github.com/users/github-actions%5Bbot%5D/subscriptions",
        "organizations_url": "https://api.github.com/users/github-actions%5Bbot%5D/orgs",
        "repos_url": "https://api.github.com/users/github-actions%5Bbot%5D/repos",
        "events_url": "https://api.github.com/users/github-actions%5Bbot%5D/events{/privacy}",
        "received_events_url": "https://api.github.com/users/github-actions%5Bbot%5D/received_events",
        "type": "Bot",
        "user_view_type": "public",
        "site_admin": false
      },
      "content_type": "application/octet-stream",
      "state": "uploaded",
      "size": 118,
      "digest": "sha256:0401ea12ddb3c0c66d9a5640171485bbd6ac042509eadb720915409731413aa8",
      "download_count": 1155,
      "created_at": "2025-10-16T03:20:43Z",
      "updated_at": "2025-10-16T03:20:43Z",
      "browser_download_url": "https://github.com/BurntSushi/ripgrep/releases/download/15.0.0/ripgrep-15.0.0-armv7-unknown-linux-gnueabihf.tar.gz.sha256"
    },
    {
      "url": "https://api.github.com/repos/BurntSushi/ripgrep/releases/assets/304881115",
      "id": 304881115,
      "node_id": "RA_kwDOAzJbyc4SLB3b",
      "name": "ripgrep-15.0.0-armv7-unknown-linux-musleabi.tar.gz",
      "label": "",
      "uploader": {
        "login": "github-actions[bot]",
        "id": 41898282,
        "node_id": "MDM6Qm90NDE4OTgyODI=",
        "avatar_url": "https://avatars.githubusercontent.com/in/15368?v=4",
        "gravatar_id": "",
        "url": "https://api.github.com/users/github-actions%5Bbot%5D",
        "html_url": "https://github.com/apps/github-actions",
        "followers_url": "https://api.github.com/users/github-actions%5Bbot%5D/followers",
        "following_url": "https://api.github.com/users/github-actions%5Bbot%5D/following{/other_user}",
        "gists_url": "https://api.github.com/users/github-actions%5Bbot%5D/gists{/gist_id}",
        "starred_url": "https://api.github.com/users/github-actions%5Bbot%5D/starred{/owner}{/repo}",
        "subscriptions_url": "https://api.github.com/users/github-actions%5Bbot%5D/subscriptions",
        "organizations_url": "https://api.github.com/users/github-actions%5Bbot%5D/orgs",
        "repos_url": "https://api.github.com/users/github-actions%5Bbot%5D/repos",
        "events_url": "https://api.github.com/users/github-actions%5Bbot%5D/events{/privacy}",
        "received_events_url": "https://api.github.com/users/github-actions%5Bbot%5D/received_events",
        "type": "Bot",
        "user_view_type": "public",
        "site_admin": false
      },
      "content_type": "application/x-gtar",
      "state": "uploaded",
      "size": 1836751,
      "digest": "sha256:1f49b435401e67439ea107709e7aac1dfc6b722071a76e991a12e224108797d7",
      "download_count": 1182,
      "created_at": "2025-10-16T03:21:09Z",
      "updated_at": "2025-10-16T03:21:10Z",
      "browser_download_url": "https://github.com/BurntSushi/ripgrep/releases/download/15.0.0/ripgrep-15.0.0-armv7-unknown-linux-musleabi.tar.gz"
    },
    {
      "url": "https://api.github.com/repos/BurntSushi/ripgrep/releases/assets/304881113",
      "id": 304881113,
      "node_id": "RA_kwDOAzJbyc4SLB3Z",
      "name": "ripgrep-15.0.0-armv7-unknown-linux-musleabi.tar.gz.sha256",
      "label": "",
      "uploader": {
        "login": "github-actions[bot]",
        "id": 41898282,
        "node_id": "MDM6Qm90NDE4OTgyODI=",
        "avatar_url": "https://avatars.githubusercontent.com/in/15368?v=4",
        "gravatar_id": "",
        "url": "https://api.github.com/users/github-actions%5Bbot%5D",
        "html_url": "https://github.com/apps/github-actions",
        "followers_url": "https://api.github.com/users/github-actions%5Bbot%5D/followers",
        "following_url": "https://api.github.com/users/github-actions%5Bbot%5D/following{/other_user}",
        "gists_url": "https://api.github.com/users/github-actions%5Bbot%5D/gists{/gist_id}",
        "starred_url": "https://api.github.com/users/github-actions%5Bbot%5D/starred{/owner}{/repo}",
        "subscriptions_url": "https://api.github.com/users/github-actions%5Bbot%5D/subscriptions",
        "organizations_url": "https://api.github.com/users/github-actions%5Bbot%5D/orgs",
        "repos_url": "https://api.github.com/users/github-actions%5Bbot%5D/repos",
        "events_url": "https://api.github.com/users/github-actions%5Bbot%5D/events{/privacy}",
        "received_events_url": "https://api.github.com/users/github-actions%5Bbot%5D/received_events",
        "type": "Bot",
        "user_view_type": "public",
        "site_admin": false
      },
      "content_type": "application/octet-stream",
      "state": "uploaded",
      "size": 117,
      "digest": "sha256:a86947ba42d4b67f9da04ba36fa64054e200993ab6e917add45df5442d6bdede",
      "download_count": 1161,
      "created_at": "2025-10-16T03:21:09Z",
      "updated_at": "2025-10-16T03:21:09Z",
      "browser_download_url": "https://github.com/BurntSushi/ripgrep/releases/download/15.0.0/ripgrep-15.0.0-armv7-unknown-linux-musleabi.tar.gz.sha256"
    },
    {
      "url": "https://api.github.com/repos/BurntSushi/ripgrep/releases/assets/304880767",
      "id": 304880767,
      "node_id": "RA_kwDOAzJbyc4SLBx_",
      "name": "ripgrep-15.0.0-armv7-unknown-linux-musleabihf.tar.gz",
      "label": "",
      "uploader": {
        "login": "github-actions[bot]",
        "id": 41898282,
        "node_id": "MDM6Qm90NDE4OTgyODI=",
        "avatar_url": "https://avatars.githubusercontent.com/in/15368?v=4",
        "gravatar_id": "",
        "url": "https://api.github.com/users/github-actions%5Bbot%5D",
        "html_url": "https://github.com/apps/github-actions",
        "followers_url": "https://api.github.com/users/github-actions%5Bbot%5D/followers",
        "following_url": "https://api.github.com/users/github-actions%5Bbot%5D/following{/other_user}",
        "gists_url": "https://api.github.com/users/github-actions%5Bbot%5D/gists{/gist_id}",
        "starred_url": "https://api.github.com/users/github-actions%5Bbot%5D/starred{/owner}{/repo}",
        "subscriptions_url": "https://api.github.com/users/github-actions%5Bbot%5D/subscriptions",
        "organizations_url": "https://api.github.com/users/github-actions%5Bbot%5D/orgs",
        "repos_url": "https://api.github.com/users/github-actions%5Bbot%5D/repos",
        "events_url": "https://api.github.com/users/github-actions%5Bbot%5D/events{/privacy}",
        "received_events_url": "https://api.github.com/users/github-actions%5Bbot%5D/received_events",
        "type": "Bot",
        "user_view_type": "public",
        "site_admin": false
      },
      "content_type": "application/x-gtar",
      "state": "uploaded",
      "size": 1844101,
      "digest": "sha256:e6fdbe890704c49d694538357f1819202163cab27e75c1ec5da8bf7c83eebaf0",
      "download_count": 1550,
      "created_at": "2025-10-16T03:19:36Z",
      "updated_at": "2025-10-16T03:19:36Z",
      "browser_download_url": "https://github.com/BurntSushi/ripgrep/releases/download/15.0.0/ripgrep-15.0.0-armv7-unknown-linux-musleabihf.tar.gz"
    },
    {
      "url": "https://api.github.com/repos/BurntSushi/ripgrep/releases/assets/304880768",
      "id": 304880768,
      "node_id": "RA_kwDOAzJbyc4SLByA",
      "name": "ripgrep-15.0.0-armv7-unknown-linux-musleabihf.tar.gz.sha256",
      "label": "",
      "uploader": {
        "login": "github-actions[bot]",
        "id": 41898282,
        "node_id": "MDM6Qm90NDE4OTgyODI=",
        "avatar_url": "https://avatars.githubusercontent.com/in/15368?v=4",
        "gravatar_id": "",
        "url": "https://api.github.com/users/github-actions%5Bbot%5D",
        "html_url": "https://github.com/apps/github-actions",
        "followers_url": "https://api.github.com/users/github-actions%5Bbot%5D/followers",
        "following_url": "https://api.github.com/users/github-actions%5Bbot%5D/following{/other_user}",
        "gists_url": "https://api.github.com/users/github-actions%5Bbot%5D/gists{/gist_id}",
        "starred_url": "https://api.github.com/users/github-actions%5Bbot%5D/starred{/owner}{/repo}",
        "subscriptions_url": "https://api.github.com/users/github-actions%5Bbot%5D/subscriptions",
        "organizations_url": "https://api.github.com/users/github-actions%5Bbot%5D/orgs",
        "repos_url": "https://api.github.com/users/github-actions%5Bbot%5D/repos",
        "events_url": "https://api.github.com/users/github-actions%5Bbot%5D/events{/privacy}",
        "received_events_url": "https://api.github.com/users/github-actions%5Bbot%5D/received_events",
        "type": "Bot",
        "user_view_type": "public",
        "site_admin": false
      },
      "content_type": "application/octet-stream",
      "state": "uploaded",
      "size": 119,
      "digest": "sha256:02558ed992c2911a7cf67d968c14e58d6b29580720d25eed8c13fc37dce25a8a",
      "download_count": 1165,
      "created_at": "2025-10-16T03:19:36Z",
      "updated_at": "2025-10-16T03:19:36Z",
      "browser_download_url": "https://github.com/BurntSushi/ripgrep/releases/download/15.0.0/ripgrep-15.0.0-armv7-unknown-linux-musleabihf.tar.gz.sha256"
    },
    {
      "url": "https://api.github.com/repos/BurntSushi/ripgrep/releases/assets/304880809",
      "id": 304880809,
      "node_id": "RA_kwDOAzJbyc4SLByp",
      "name": "ripgrep-15.0.0-i686-pc-windows-msvc.zip",
      "label": "",
      "uploader": {
        "login": "github-actions[bot]",
        "id": 41898282,
        "node_id": "MDM6Qm90NDE4OTgyODI=",
        "avatar_url": "https://avatars.githubusercontent.com/in/15368?v=4",
        "gravatar_id": "",
        "url": "https://api.github.com/users/github-actions%5Bbot%5D",
        "html_url": "https://github.com/apps/github-actions",
        "followers_url": "https://api.github.com/users/github-actions%5Bbot%5D/followers",
        "following_url": "https://api.github.com/users/github-actions%5Bbot%5D/following{/other_user}",
        "gists_url": "https://api.github.com/users/github-actions%5Bbot%5D/gists{/gist_id}",
        "starred_url": "https://api.github.com/users/github-actions%5Bbot%5D/starred{/owner}{/repo}",
        "subscriptions_url": "https://api.github.com/users/github-actions%5Bbot%5D/subscriptions",
        "organizations_url": "https://api.github.com/users/github-actions%5Bbot%5D/orgs",
        "repos_url": "https://api.github.com/users/github-actions%5Bbot%5D/repos",
        "events_url": "https://api.github.com/users/github-actions%5Bbot%5D/events{/privacy}",
        "received_events_url": "https://api.github.com/users/github-actions%5Bbot%5D/received_events",
        "type": "Bot",
        "user_view_type": "public",
        "site_admin": false
      },
      "content_type": "application/zip",
      "state": "uploaded",
      "size": 1670048,
      "digest": "sha256:acb9918e9f3a88bd171143d663ffb12e8ab765b48bb449f8e7d8f1c7c1bd8311",
      "download_count": 1597,
      "created_at": "2025-10-16T03:19:48Z",
      "updated_at": "2025-10-16T03:19:49Z",
      "browser_download_url": "https://github.com/BurntSushi/ripgrep/releases/download/15.0.0/ripgrep-15.0.0-i686-pc-windows-msvc.zip"
    },
    {
      "url": "https://api.github.com/repos/BurntSushi/ripgrep/releases/assets/304880810",
      "id": 304880810,
      "node_id": "RA_kwDOAzJbyc4SLByq",
      "name": "ripgrep-15.0.0-i686-pc-windows-msvc.zip.sha256",
      "label": "",
      "uploader": {
        "login": "github-actions[bot]",
        "id": 41898282,
        "node_id": "MDM6Qm90NDE4OTgyODI=",
        "avatar_url": "https://avatars.githubusercontent.com/in/15368?v=4",
        "gravatar_id": "",
        "url": "https://api.github.com/users/github-actions%5Bbot%5D",
        "html_url": "https://github.com/apps/github-actions",
        "followers_url": "https://api.github.com/users/github-actions%5Bbot%5D/followers",
        "following_url": "https://api.github.com/users/github-actions%5Bbot%5D/following{/other_user}",
        "gists_url": "https://api.github.com/users/github-actions%5Bbot%5D/gists{/gist_id}",
        "starred_url": "https://api.github.com/users/github-actions%5Bbot%5D/starred{/owner}{/repo}",
        "subscriptions_url": "https://api.github.com/users/github-actions%5Bbot%5D/subscriptions",
        "organizations_url": "https://api.github.com/users/github-actions%5Bbot%5D/orgs",
        "repos_url": "https://api.github.com/users/github-actions%5Bbot%5D/repos",
        "events_url": "https://api.github.com/users/github-actions%5Bbot%5D/events{/privacy}",
        "received_events_url": "https://api.github.com/users/github-actions%5Bbot%5D/received_events",
        "type": "Bot",
        "user_view_type": "public",
        "site_admin": false
      },
      "content_type": "application/octet-stream",
      "state": "uploaded",
      "size": 176,
      "digest": "sha256:a9722f3de6ab8a6acb91863ee68e9e9afebab842857a7104b69bf9eef66b6686",
      "download_count": 1165,
      "created_at": "2025-10-16T03:19:48Z",
      "updated_at": "2025-10-16T03:19:48Z",
      "browser_download_url": "https://github.com/BurntSushi/ripgrep/releases/download/15.0.0/ripgrep-15.0.0-i686-pc-windows-msvc.zip.sha256"
    },
    {
      "url": "https://api.github.com/repos/BurntSushi/ripgrep/releases/assets/304880784",
      "id": 304880784,
      "node_id": "RA_kwDOAzJbyc4SLByQ",
      "name": "ripgrep-15.0.0-i686-unknown-linux-gnu.tar.gz",
      "label": "",
      "uploader": {
        "login": "github-actions[bot]",
        "id": 41898282,
        "node_id": "MDM6Qm90NDE4OTgyODI=",
        "avatar_url": "https://avatars.githubusercontent.com/in/15368?v=4",
        "gravatar_id": "",
        "url": "https://api.github.com/users/github-actions%5Bbot%5D",
        "html_url": "https://github.com/apps/github-actions",
        "followers_url": "https://api.github.com/users/github-actions%5Bbot%5D/followers",
        "following_url": "https://api.github.com/users/github-actions%5Bbot%5D/following{/other_user}",
        "gists_url": "https://api.github.com/users/github-actions%5Bbot%5D/gists{/gist_id}",
        "starred_url": "https://api.github.com/users/github-actions%5Bbot%5D/starred{/owner}{/repo}",
        "subscriptions_url": "https://api.github.com/users/github-actions%5Bbot%5D/subscriptions",
        "organizations_url": "https://api.github.com/users/github-actions%5Bbot%5D/orgs",
        "repos_url": "https://api.github.com/users/github-actions%5Bbot%5D/repos",
        "events_url": "https://api.github.com/users/github-actions%5Bbot%5D/events{/privacy}",
        "received_events_url": "https://api.github.com/users/github-actions%5Bbot%5D/received_events",
        "type": "Bot",
        "user_view_type": "public",
        "site_admin": false
      },
      "content_type": "application/x-gtar",
      "state": "uploaded",
      "size": 1952857,
      "digest": "sha256:9a614b1c5014a1e9aa67aa7639fc47ee39bba02714589f43411466f75def1d3b",
      "download_count": 1211,
      "created_at": "2025-10-16T03:19:41Z",
      "updated_at": "2025-10-16T03:19:41Z",
      "browser_download_url": "https://github.com/BurntSushi/ripgrep/releases/download/15.0.0/ripgrep-15.0.0-i686-unknown-linux-gnu.tar.gz"
    },
    {
      "url": "https://api.github.com/repos/BurntSushi/ripgrep/releases/assets/304880785",
      "id": 304880785,
      "node_id": "RA_kwDOAzJbyc4SLByR",
      "name": "ripgrep-15.0.0-i686-unknown-linux-gnu.tar.gz.sha256",
      "label": "",
      "uploader": {
        "login": "github-actions[bot]",
        "id": 41898282,
        "node_id": "MDM6Qm90NDE4OTgyODI=",
        "avatar_url": "https://avatars.githubusercontent.com/in/15368?v=4",
        "gravatar_id": "",
        "url": "https://api.github.com/users/github-actions%5Bbot%5D",
        "html_url": "https://github.com/apps/github-actions",
        "followers_url": "https://api.github.com/users/github-actions%5Bbot%5D/followers",
        "following_url": "https://api.github.com/users/github-actions%5Bbot%5D/following{/other_user}",
        "gists_url": "https://api.github.com/users/github-actions%5Bbot%5D/gists{/gist_id}",
        "starred_url": "https://api.github.com/users/github-actions%5Bbot%5D/starred{/owner}{/repo}",
        "subscriptions_url": "https://api.github.com/users/github-actions%5Bbot%5D/subscriptions",
        "organizations_url": "https://api.github.com/users/github-actions%5Bbot%5D/orgs",
        "repos_url": "https://api.github.com/users/github-actions%5Bbot%5D/repos",
        "events_url": "https://api.github.com/users/github-actions%5Bbot%5D/events{/privacy}",
        "received_events_url": "https://api.github.com/users/github-actions%5Bbot%5D/received_events",
        "type": "Bot",
        "user_view_type": "public",
        "site_admin": false
      },
      "content_type": "application/octet-stream",
      "state": "uploaded",
      "size": 111,
      "digest": "sha256:0deab1b619a75f599b356611e89873b17324ef3ee4ba6360eb160aa4bb3861c1",
      "download_count": 1159,
      "created_at": "2025-10-16T03:19:41Z",
      "updated_at": "2025-10-16T03:19:41Z",
      "browser_download_url": "https://github.com/BurntSushi/ripgrep/releases/download/15.0.0/ripgrep-15.0.0-i686-unknown-linux-gnu.tar.gz.sha256"
    },
    {
      "url": "https://api.github.com/repos/BurntSushi/ripgrep/releases/assets/304880779",
      "id": 304880779,
      "node_id": "RA_kwDOAzJbyc4SLByL",
      "name": "ripgrep-15.0.0-s390x-unknown-linux-gnu.tar.gz",
      "label": "",
      "uploader": {
        "login": "github-actions[bot]",
        "id": 41898282,
        "node_id": "MDM6Qm90NDE4OTgyODI=",
        "avatar_url": "https://avatars.githubusercontent.com/in/15368?v=4",
        "gravatar_id": "",
        "url": "https://api.github.com/users/github-actions%5Bbot%5D",
        "html_url": "https://github.com/apps/github-actions",
        "followers_url": "https://api.github.com/users/github-actions%5Bbot%5D/followers",
        "following_url": "https://api.github.com/users/github-actions%5Bbot%5D/following{/other_user}",
        "gists_url": "https://api.github.com/users/github-actions%5Bbot%5D/gists{/gist_id}",
        "starred_url": "https://api.github.com/users/github-actions%5Bbot%5D/starred{/owner}{/repo}",
        "subscriptions_url": "https://api.github.com/users/github-actions%5Bbot%5D/subscriptions",
        "organizations_url": "https://api.github.com/users/github-actions%5Bbot%5D/orgs",
        "repos_url": "https://api.github.com/users/github-actions%5Bbot%5D/repos",
        "events_url": "https://api.github.com/users/github-actions%5Bbot%5D/events{/privacy}",
        "received_events_url": "https://api.github.com/users/github-actions%5Bbot%5D/received_events",
        "type": "Bot",
        "user_view_type": "public",
        "site_admin": false
      },
      "content_type": "application/x-gtar",
      "state": "uploaded",
      "size": 2431790,
      "digest": "sha256:95c24c733210c097557c6534dced233e8d7aaa4436cd808a1e01ab9338ac7951",
      "download_count": 1168,
      "created_at": "2025-10-16T03:19:38Z",
      "updated_at": "2025-10-16T03:19:38Z",
      "browser_download_url": "https://github.com/BurntSushi/ripgrep/releases/download/15.0.0/ripgrep-15.0.0-s390x-unknown-linux-gnu.tar.gz"
    },
    {
      "url": "https://api.github.com/repos/BurntSushi/ripgrep/releases/assets/304880780",
      "id": 304880780,
      "node_id": "RA_kwDOAzJbyc4SLByM",
      "name": "ripgrep-15.0.0-s390x-unknown-linux-gnu.tar.gz.sha256",
      "label": "",
      "uploader": {
        "login": "github-actions[bot]",
        "id": 41898282,
        "node_id": "MDM6Qm90NDE4OTgyODI=",
        "avatar_url": "https://avatars.githubusercontent.com/in/15368?v=4",
        "gravatar_id": "",
        "url": "https://api.github.com/users/github-actions%5Bbot%5D",
        "html_url": "https://github.com/apps/github-actions",
        "followers_url": "https://api.github.com/users/github-actions%5Bbot%5D/followers",
        "following_url": "https://api.github.com/users/github-actions%5Bbot%5D/following{/other_user}",
        "gists_url": "https://api.github.com/users/github-actions%5Bbot%5D/gists{/gist_id}",
        "starred_url": "https://api.github.com/users/github-actions%5Bbot%5D/starred{/owner}{/repo}",
        "subscriptions_url": "https://api.github.com/users/github-actions%5Bbot%5D/subscriptions",
        "organizations_url": "https://api.github.com/users/github-actions%5Bbot%5D/orgs",
        "repos_url": "https://api.github.com/users/github-actions%5Bbot%5D/repos",
        "events_url": "https://api.github.com/users/github-actions%5Bbot%5D/events{/privacy}",
        "received_events_url": "https://api.github.com/users/github-actions%5Bbot%5D/received_events",
        "type": "Bot",
        "user_view_type": "public",
        "site_admin": false
      },
      "content_type": "application/octet-stream",
      "state": "uploaded",
      "size": 112,
      "digest": "sha256:fc90e34937e69c59522e8f13990b271c08909e54e4ef59eced3e2191e2d4bdd0",
      "download_count": 1152,
      "created_at": "2025-10-16T03:19:38Z",
      "updated_at": "2025-10-16T03:19:38Z",
      "browser_download_url": "https://github.com/BurntSushi/ripgrep/releases/download/15.0.0/ripgrep-15.0.0-s390x-unknown-linux-gnu.tar.gz.sha256"
    },
    {
      "url": "https://api.github.com/repos/BurntSushi/ripgrep/releases/assets/304880656",
      "id": 304880656,
      "node_id": "RA_kwDOAzJbyc4SLBwQ",
      "name": "ripgrep-15.0.0-x86_64-apple-darwin.tar.gz",
      "label": "",
      "uploader": {
        "login": "github-actions[bot]",
        "id": 41898282,
        "node_id": "MDM6Qm90NDE4OTgyODI=",
        "avatar_url": "https://avatars.githubusercontent.com/in/15368?v=4",
        "gravatar_id": "",
        "url": "https://api.github.com/users/github-actions%5Bbot%5D",
        "html_url": "https://github.com/apps/github-actions",
        "followers_url": "https://api.github.com/users/github-actions%5Bbot%5D/followers",
        "following_url": "https://api.github.com/users/github-actions%5Bbot%5D/following{/other_user}",
        "gists_url": "https://api.github.com/users/github-actions%5Bbot%5D/gists{/gist_id}",
        "starred_url": "https://api.github.com/users/github-actions%5Bbot%5D/starred{/owner}{/repo}",
        "subscriptions_url": "https://api.github.com/users/github-actions%5Bbot%5D/subscriptions",
        "organizations_url": "https://api.github.com/users/github-actions%5Bbot%5D/orgs",
        "repos_url": "https://api.github.com/users/github-actions%5Bbot%5D/repos",
        "events_url": "https://api.github.com/users/github-actions%5Bbot%5D/events{/privacy}",
        "received_events_url": "https://api.github.com/users/github-actions%5Bbot%5D/received_events",
        "type": "Bot",
        "user_view_type": "public",
        "site_admin": false
      },
      "content_type": "application/x-gtar",
      "state": "uploaded",
      "size": 1887368,
      "digest": "sha256:44128c733d127ddbda461e01225a68b5f9997cfe7635242a797f645ca674a71a",
      "download_count": 3024,
      "created_at": "2025-10-16T03:19:11Z",
      "updated_at": "2025-10-16T03:19:12Z",
      "browser_download_url": "https://github.com/BurntSushi/ripgrep/releases/download/15.0.0/ripgrep-15.0.0-x86_64-apple-darwin.tar.gz"
    },
    {
      "url": "https://api.github.com/repos/BurntSushi/ripgrep/releases/assets/304880658",
      "id": 304880658,
      "node_id": "RA_kwDOAzJbyc4SLBwS",
      "name": "ripgrep-15.0.0-x86_64-apple-darwin.tar.gz.sha256",
      "label": "",
      "uploader": {
        "login": "github-actions[bot]",
        "id": 41898282,
        "node_id": "MDM6Qm90NDE4OTgyODI=",
        "avatar_url": "https://avatars.githubusercontent.com/in/15368?v=4",
        "gravatar_id": "",
        "url": "https://api.github.com/users/github-actions%5Bbot%5D",
        "html_url": "https://github.com/apps/github-actions",
        "followers_url": "https://api.github.com/users/github-actions%5Bbot%5D/followers",
        "following_url": "https://api.github.com/users/github-actions%5Bbot%5D/following{/other_user}",
        "gists_url": "https://api.github.com/users/github-actions%5Bbot%5D/gists{/gist_id}",
        "starred_url": "https://api.github.com/users/github-actions%5Bbot%5D/starred{/owner}{/repo}",
        "subscriptions_url": "https://api.github.com/users/github-actions%5Bbot%5D/subscriptions",
        "organizations_url": "https://api.github.com/users/github-actions%5Bbot%5D/orgs",
        "repos_url": "https://api.github.com/users/github-actions%5Bbot%5D/repos",
        "events_url": "https://api.github.com/users/github-actions%5Bbot%5D/events{/privacy}",
        "received_events_url": "https://api.github.com/users/github-actions%5Bbot%5D/received_events",
        "type": "Bot",
        "user_view_type": "public",
        "site_admin": false
      },
      "content_type": "application/octet-stream",
      "state": "uploaded",
      "size": 108,
      "digest": "sha256:6ffb1e07d190e80981024c4fd5adede448d4d37a6aeed5d245ed4d5ec62dcd4c",
      "download_count": 1206,
      "created_at": "2025-10-16T03:19:11Z",
      "updated_at": "2025-10-16T03:19:11Z",
      "browser_download_url": "https://github.com/BurntSushi/ripgrep/releases/download/15.0.0/ripgrep-15.0.0-x86_64-apple-darwin.tar.gz.sha256"
    },
    {
      "url": "https://api.github.com/repos/BurntSushi/ripgrep/releases/assets/304880788",
      "id": 304880788,
      "node_id": "RA_kwDOAzJbyc4SLByU",
      "name": "ripgrep-15.0.0-x86_64-pc-windows-gnu.zip",
      "label": "",
      "uploader": {
        "login": "github-actions[bot]",
        "id": 41898282,
        "node_id": "MDM6Qm90NDE4OTgyODI=",
        "avatar_url": "https://avatars.githubusercontent.com/in/15368?v=4",
        "gravatar_id": "",
        "url": "https://api.github.com/users/github-actions%5Bbot%5D",
        "html_url": "https://github.com/apps/github-actions",
        "followers_url": "https://api.github.com/users/github-actions%5Bbot%5D/followers",
        "following_url": "https://api.github.com/users/github-actions%5Bbot%5D/following{/other_user}",
        "gists_url": "https://api.github.com/users/github-actions%5Bbot%5D/gists{/gist_id}",
        "starred_url": "https://api.github.com/users/github-actions%5Bbot%5D/starred{/owner}{/repo}",
        "subscriptions_url": "https://api.github.com/users/github-actions%5Bbot%5D/subscriptions",
        "organizations_url": "https://api.github.com/users/github-actions%5Bbot%5D/orgs",
        "repos_url": "https://api.github.com/users/github-actions%5Bbot%5D/repos",
        "events_url": "https://api.github.com/users/github-actions%5Bbot%5D/events{/privacy}",
        "received_events_url": "https://api.github.com/users/github-actions%5Bbot%5D/received_events",
        "type": "Bot",
        "user_view_type": "public",
        "site_admin": false
      },
      "content_type": "application/zip",
      "state": "uploaded",
      "size": 1897663,
      "digest": "sha256:2da5362849a82c847923524cf983f134cefb07272501bff3647b4d035dd28528",
      "download_count": 2437,
      "created_at": "2025-10-16T03:19:42Z",
      "updated_at": "2025-10-16T03:19:43Z",
      "browser_download_url": "https://github.com/BurntSushi/ripgrep/releases/download/15.0.0/ripgrep-15.0.0-x86_64-pc-windows-gnu.zip"
    },
    {
      "url": "https://api.github.com/repos/BurntSushi/ripgrep/releases/assets/304880787",
      "id": 304880787,
      "node_id": "RA_kwDOAzJbyc4SLByT",
      "name": "ripgrep-15.0.0-x86_64-pc-windows-gnu.zip.sha256",
      "label": "",
      "uploader": {
        "login": "github-actions[bot]",
        "id": 41898282,
        "node_id": "MDM6Qm90NDE4OTgyODI=",
        "avatar_url": "https://avatars.githubusercontent.com/in/15368?v=4",
        "gravatar_id": "",
        "url": "https://api.github.com/users/github-actions%5Bbot%5D",
        "html_url": "https://github.com/apps/github-actions",
        "followers_url": "https://api.github.com/users/github-actions%5Bbot%5D/followers",
        "following_url": "https://api.github.com/users/github-actions%5Bbot%5D/following{/other_user}",
        "gists_url": "https://api.github.com/users/github-actions%5Bbot%5D/gists{/gist_id}",
        "starred_url": "https://api.github.com/users/github-actions%5Bbot%5D/starred{/owner}{/repo}",
        "subscriptions_url": "https://api.github.com/users/github-actions%5Bbot%5D/subscriptions",
        "organizations_url": "https://api.github.com/users/github-actions%5Bbot%5D/orgs",
        "repos_url": "https://api.github.com/users/github-actions%5Bbot%5D/repos",
        "events_url": "https://api.github.com/users/github-actions%5Bbot%5D/events{/privacy}",
        "received_events_url": "https://api.github.com/users/github-actions%5Bbot%5D/received_events",
        "type": "Bot",
        "user_view_type": "public",
        "site_admin": false
      },
      "content_type": "application/octet-stream",
      "state": "uploaded",
      "size": 177,
      "digest": "sha256:f13d1ed45ea74d6e750da0af4d0f5a7f58d3b00a030082aa604a0dd961b95c63",
      "download_count": 1174,
      "created_at": "2025-10-16T03:19:42Z",
      "updated_at": "2025-10-16T03:19:42Z",
      "browser_download_url": "https://github.com/BurntSushi/ripgrep/releases/download/15.0.0/ripgrep-15.0.0-x86_64-pc-windows-gnu.zip.sha256"
    },
    {
      "url": "https://api.github.com/repos/BurntSushi/ripgrep/releases/assets/304880754",
      "id": 304880754,
      "node_id": "RA_kwDOAzJbyc4SLBxy",
      "name": "ripgrep-15.0.0-x86_64-pc-windows-msvc.zip",
      "label": "",
      "uploader": {
        "login": "github-actions[bot]",
        "id": 41898282,
        "node_id": "MDM6Qm90NDE4OTgyODI=",
        "avatar_url": "https://avatars.githubusercontent.com/in/15368?v=4",
        "gravatar_id": "",
        "url": "https://api.github.com/users/github-actions%5Bbot%5D",
        "html_url": "https://github.com/apps/github-actions",
        "followers_url": "https://api.github.com/users/github-actions%5Bbot%5D/followers",
        "following_url": "https://api.github.com/users/github-actions%5Bbot%5D/following{/other_user}",
        "gists_url": "https://api.github.com/users/github-actions%5Bbot%5D/gists{/gist_id}",
        "starred_url": "https://api.github.com/users/github-actions%5Bbot%5D/starred{/owner}{/repo}",
        "subscriptions_url": "https://api.github.com/users/github-actions%5Bbot%5D/subscriptions",
        "organizations_url": "https://api.github.com/users/github-actions%5Bbot%5D/orgs",
        "repos_url": "https://api.github.com/users/github-actions%5Bbot%5D/repos",
        "events_url": "https://api.github.com/users/github-actions%5Bbot%5D/events{/privacy}",
        "received_events_url": "https://api.github.com/users/github-actions%5Bbot%5D/received_events",
        "type": "Bot",
        "user_view_type": "public",
        "site_admin": false
      },
      "content_type": "application/zip",
      "state": "uploaded",
      "size": 1805250,
      "digest": "sha256:21a98bf42c4da97ca543c010e764cc6dec8b9b7538d05f8d21874016385e0860",
      "download_count": 17445,
      "created_at": "2025-10-16T03:19:33Z",
      "updated_at": "2025-10-16T03:19:34Z",
      "browser_download_url": "https://github.com/BurntSushi/ripgrep/releases/download/15.0.0/ripgrep-15.0.0-x86_64-pc-windows-msvc.zip"
    },
    {
      "url": "https://api.github.com/repos/BurntSushi/ripgrep/releases/assets/304880755",
      "id": 304880755,
      "node_id": "RA_kwDOAzJbyc4SLBxz",
      "name": "ripgrep-15.0.0-x86_64-pc-windows-msvc.zip.sha256",
      "label": "",
      "uploader": {
        "login": "github-actions[bot]",
        "id": 41898282,
        "node_id": "MDM6Qm90NDE4OTgyODI=",
        "avatar_url": "https://avatars.githubusercontent.com/in/15368?v=4",
        "gravatar_id": "",
        "url": "https://api.github.com/users/github-actions%5Bbot%5D",
        "html_url": "https://github.com/apps/github-actions",
        "followers_url": "https://api.github.com/users/github-actions%5Bbot%5D/followers",
        "following_url": "https://api.github.com/users/github-actions%5Bbot%5D/following{/other_user}",
        "gists_url": "https://api.github.com/users/github-actions%5Bbot%5D/gists{/gist_id}",
        "starred_url": "https://api.github.com/users/github-actions%5Bbot%5D/starred{/owner}{/repo}",
        "subscriptions_url": "https://api.github.com/users/github-actions%5Bbot%5D/subscriptions",
        "organizations_url": "https://api.github.com/users/github-actions%5Bbot%5D/orgs",
        "repos_url": "https://api.github.com/users/github-actions%5Bbot%5D/repos",
        "events_url": "https://api.github.com/users/github-actions%5Bbot%5D/events{/privacy}",
        "received_events_url": "https://api.github.com/users/github-actions%5Bbot%5D/received_events",
        "type": "Bot",
        "user_view_type": "public",
        "site_admin": false
      },
      "content_type": "application/octet-stream",
      "state": "uploaded",
      "size": 178,
      "digest": "sha256:59c7ff3403cf7e4429478fbb025fa3241569a65b310862c3150e4de1a6c6a7f7",
      "download_count": 1208,
      "created_at": "2025-10-16T03:19:34Z",
      "updated_at": "2025-10-16T03:19:34Z",
      "browser_download_url": "https://github.com/BurntSushi/ripgrep/releases/download/15.0.0/ripgrep-15.0.0-x86_64-pc-windows-msvc.zip.sha256"
    },
    {
      "url": "https://api.github.com/repos/BurntSushi/ripgrep/releases/assets/304882372",
      "id": 304882372,
      "node_id": "RA_kwDOAzJbyc4SLCLE",
      "name": "ripgrep-15.0.0-x86_64-unknown-linux-musl.tar.gz",
      "label": "",
      "uploader": {
        "login": "github-actions[bot]",
        "id": 41898282,
        "node_id": "MDM6Qm90NDE4OTgyODI=",
        "avatar_url": "https://avatars.githubusercontent.com/in/15368?v=4",
        "gravatar_id": "",
        "url": "https://api.github.com/users/github-actions%5Bbot%5D",
        "html_url": "https://github.com/apps/github-actions",
        "followers_url": "https://api.github.com/users/github-actions%5Bbot%5D/followers",
        "following_url": "https://api.github.com/users/github-actions%5Bbot%5D/following{/other_user}",
        "gists_url": "https://api.github.com/users/github-actions%5Bbot%5D/gists{/gist_id}",
        "starred_url": "https://api.github.com/users/github-actions%5Bbot%5D/starred{/owner}{/repo}",
        "subscriptions_url": "https://api.github.com/users/github-actions%5Bbot%5D/subscriptions",
        "organizations_url": "https://api.github.com/users/github-actions%5Bbot%5D/orgs",
        "repos_url": "https://api.github.com/users/github-actions%5Bbot%5D/repos",
        "events_url": "https://api.github.com/users/github-actions%5Bbot%5D/events{/privacy}",
        "received_events_url": "https://api.github.com/users/github-actions%5Bbot%5D/received_events",
        "type": "Bot",
        "user_view_type": "public",
        "site_admin": false
      },
      "content_type": "application/x-gtar",
      "state": "uploaded",
      "size": 2262100,
      "digest": "sha256:253ad0fd5fef0d64cba56c70dccdacc1916d4ed70ad057cc525fcdb0c3bbd2a7",
      "download_count": 35211,
      "created_at": "2025-10-16T03:26:46Z",
      "updated_at": "2025-10-16T03:26:46Z",
      "browser_download_url": "https://github.com/BurntSushi/ripgrep/releases/download/15.0.0/ripgrep-15.0.0-x86_64-unknown-linux-musl.tar.gz"
    },
    {
      "url": "https://api.github.com/repos/BurntSushi/ripgrep/releases/assets/304882371",
      "id": 304882371,
      "node_id": "RA_kwDOAzJbyc4SLCLD",
      "name": "ripgrep-15.0.0-x86_64-unknown-linux-musl.tar.gz.sha256",
      "label": "",
      "uploader": {
        "login": "github-actions[bot]",
        "id": 41898282,
        "node_id": "MDM6Qm90NDE4OTgyODI=",
        "avatar_url": "https://avatars.githubusercontent.com/in/15368?v=4",
        "gravatar_id": "",
        "url": "https://api.github.com/users/github-actions%5Bbot%5D",
        "html_url": "https://github.com/apps/github-actions",
        "followers_url": "https://api.github.com/users/github-actions%5Bbot%5D/followers",
        "following_url": "https://api.github.com/users/github-actions%5Bbot%5D/following{/other_user}",
        "gists_url": "https://api.github.com/users/github-actions%5Bbot%5D/gists{/gist_id}",
        "starred_url": "https://api.github.com/users/github-actions%5Bbot%5D/starred{/owner}{/repo}",
        "subscriptions_url": "https://api.github.com/users/github-actions%5Bbot%5D/subscriptions",
        "organizations_url": "https://api.github.com/users/github-actions%5Bbot%5D/orgs",
        "repos_url": "https://api.github.com/users/github-actions%5Bbot%5D/repos",
        "events_url": "https://api.github.com/users/github-actions%5Bbot%5D/events{/privacy}",
        "received_events_url": "https://api.github.com/users/github-actions%5Bbot%5D/received_events",
        "type": "Bot",
        "user_view_type": "public",
        "site_admin": false
      },
      "content_type": "application/octet-stream",
      "state": "uploaded",
      "size": 114,
      "digest": "sha256:859b5796d63d7f3037f4ca95220ca3a4670332317e1561af3deda43ef8d271ba",
      "download_count": 2958,
      "created_at": "2025-10-16T03:26:46Z",
      "updated_at": "2025-10-16T03:26:46Z",
      "browser_download_url": "https://github.com/BurntSushi/ripgrep/releases/download/15.0.0/ripgrep-15.0.0-x86_64-unknown-linux-musl.tar.gz.sha256"
    },
    {
      "url": "https://api.github.com/repos/BurntSushi/ripgrep/releases/assets/304881026",
      "id": 304881026,
      "node_id": "RA_kwDOAzJbyc4SLB2C",
      "name": "ripgrep_15.0.0-1_amd64.deb",
      "label": "",
      "uploader": {
        "login": "github-actions[bot]",
        "id": 41898282,
        "node_id": "MDM6Qm90NDE4OTgyODI=",
        "avatar_url": "https://avatars.githubusercontent.com/in/15368?v=4",
        "gravatar_id": "",
        "url": "https://api.github.com/users/github-actions%5Bbot%5D",
        "html_url": "https://github.com/apps/github-actions",
        "followers_url": "https://api.github.com/users/github-actions%5Bbot%5D/followers",
        "following_url": "https://api.github.com/users/github-actions%5Bbot%5D/following{/other_user}",
        "gists_url": "https://api.github.com/users/github-actions%5Bbot%5D/gists{/gist_id}",
        "starred_url": "https://api.github.com/users/github-actions%5Bbot%5D/starred{/owner}{/repo}",
        "subscriptions_url": "https://api.github.com/users/github-actions%5Bbot%5D/subscriptions",
        "organizations_url": "https://api.github.com/users/github-actions%5Bbot%5D/orgs",
        "repos_url": "https://api.github.com/users/github-actions%5Bbot%5D/repos",
        "events_url": "https://api.github.com/users/github-actions%5Bbot%5D/events{/privacy}",
        "received_events_url": "https://api.github.com/users/github-actions%5Bbot%5D/received_events",
        "type": "Bot",
        "user_view_type": "public",
        "site_admin": false
      },
      "content_type": "application/x-debian-package",
      "state": "uploaded",
      "size": 1702852,
      "digest": "sha256:ec08b128f8774c256f87b8f79def4f4930c769e21e980ec9a80e27f4f5f76759",
      "download_count": 1963,
      "created_at": "2025-10-16T03:20:39Z",
      "updated_at": "2025-10-16T03:20:39Z",
      "browser_download_url": "https://github.com/BurntSushi/ripgrep/releases/download/15.0.0/ripgrep_15.0.0-1_amd64.deb"
    },
    {
      "url": "https://api.github.com/repos/BurntSushi/ripgrep/releases/assets/304881025",
      "id": 304881025,
      "node_id": "RA_kwDOAzJbyc4SLB2B",
      "name": "ripgrep_15.0.0-1_amd64.deb.sha256",
      "label": "",
      "uploader": {
        "login": "github-actions[bot]",
        "id": 41898282,
        "node_id": "MDM6Qm90NDE4OTgyODI=",
        "avatar_url": "https://avatars.githubusercontent.com/in/15368?v=4",
        "gravatar_id": "",
        "url": "https://api.github.com/users/github-actions%5Bbot%5D",
        "html_url": "https://github.com/apps/github-actions",
        "followers_url": "https://api.github.com/users/github-actions%5Bbot%5D/followers",
        "following_url": "https://api.github.com/users/github-actions%5Bbot%5D/following{/other_user}",
        "gists_url": "https://api.github.com/users/github-actions%5Bbot%5D/gists{/gist_id}",
        "starred_url": "https://api.github.com/users/github-actions%5Bbot%5D/starred{/owner}{/repo}",
        "subscriptions_url": "https://api.github.com/users/github-actions%5Bbot%5D/subscriptions",
        "organizations_url": "https://api.github.com/users/github-actions%5Bbot%5D/orgs",
        "repos_url": "https://api.github.com/users/github-actions%5Bbot%5D/repos",
        "events_url": "https://api.github.com/users/github-actions%5Bbot%5D/events{/privacy}",
        "received_events_url": "https://api.github.com/users/github-actions%5Bbot%5D/received_events",
        "type": "Bot",
        "user_view_type": "public",
        "site_admin": false
      },
      "content_type": "application/octet-stream",
      "state": "uploaded",
      "size": 93,
      "digest": "sha256:1836c681392d54c0c712e84181d1233b6186b23d8861284553a7b76f635ab4e0",
      "download_count": 1216,
      "created_at": "2025-10-16T03:20:39Z",
      "updated_at": "2025-10-16T03:20:39Z",
      "browser_download_url": "https://github.com/BurntSushi/ripgrep/releases/download/15.0.0/ripgrep_15.0.0-1_amd64.deb.sha256"
    }
  ],
  "tarball_url": "https://api.github.com/repos/BurntSushi/ripgrep/tarball/15.0.0",
  "zipball_url": "https://api.github.com/repos/BurntSushi/ripgrep/zipball/15.0.0",
  "body": "[Sponsorship is appreciated!](https://github.com/sponsors/BurntSushi/)\r\n\r\nripgrep 15 is a new major version release of ripgrep that mostly has bug fixes,\r\nsome minor performance improvements and minor new features.\r\n\r\n> In case you haven't heard of it before, ripgrep is a line-oriented search\r\n> tool that recursively searches the current directory for a regex pattern.\r\n> By default, ripgrep will respect gitignore rules and automatically skip\r\n> hidden files/directories and binary files.\r\n\r\nHere are some highlights:\r\n\r\n* Several bugs around gitignore matching have been fixed. This includes\r\n  a commonly reported bug related to applying gitignore rules from parent\r\n  directories.\r\n* A memory usage regression when handling very large gitignore files has been\r\n  fixed.\r\n* `rg -vf file`, where `file` is empty, now matches everything.\r\n* The `-r/--replace` flag now works with `--json`.\r\n* A subset of Jujutsu (`jj`) repositories are now treated as if they were git\r\n  repositories. That is, ripgrep will respect `jj`'s gitignores.\r\n* Globs can now use nested curly braces.\r\n\r\nPlatform support:\r\n\r\n* `aarch64` for Windows now has release artifacts.\r\n* `powerpc64` no longer has release artifacts generated for it. The CI\r\n  release workflow stopped working, and I didn't deem it worth my time to\r\n  debug it. If someone wants this and can test it, I'd be happy to add it\r\n  back.\r\n* ripgrep binaries are now compiled with full LTO enabled. You may notice\r\n  small performance improvements from this and a modest decrease in binary\r\n  size.\r\n\r\nPerformance improvements:\r\n\r\n* [PERF #2111](https://github.com/BurntSushi/ripgrep/issues/2111):\r\n  Don't resolve helper binaries on Windows when `-z/--search-zip` isn't used.\r\n* [PERF #2865](https://github.com/BurntSushi/ripgrep/pull/2865):\r\n  Avoid using path canonicalization on Windows when emitting hyperlinks.\r\n* [PERF #3184](https://github.com/BurntSushi/ripgrep/pull/3184):\r\n  Improve performance of large values with `-A/--after-context`.\r\n\r\nBug fixes:\r\n\r\n* [BUG #829](https://github.com/BurntSushi/ripgrep/issues/829),\r\n  [BUG #2731](https://github.com/BurntSushi/ripgrep/issues/2731),\r\n  [BUG #2747](https://github.com/BurntSushi/ripgrep/issues/2747),\r\n  [BUG #2770](https://github.com/BurntSushi/ripgrep/issues/2770),\r\n  [BUG #2778](https://github.com/BurntSushi/ripgrep/issues/2778),\r\n  [BUG #2836](https://github.com/BurntSushi/ripgrep/issues/2836),\r\n  [BUG #2933](https://github.com/BurntSushi/ripgrep/pull/2933),\r\n  [BUG #3067](https://github.com/BurntSushi/ripgrep/pull/3067):\r\n  Fix bug related to gitignores from parent directories.\r\n* [BUG #1332](https://github.com/BurntSushi/ripgrep/issues/1332),\r\n  [BUG #3001](https://github.com/BurntSushi/ripgrep/issues/3001):\r\n  Make `rg -vf file` where `file` is empty match everything.\r\n* [BUG #2177](https://github.com/BurntSushi/ripgrep/issues/2177):\r\n  Ignore a UTF-8 BOM marker at the start of `.gitignore` (and similar files).\r\n* [BUG #2750](https://github.com/BurntSushi/ripgrep/issues/2750):\r\n  Fix memory usage regression for some truly large gitignore files.\r\n* [BUG #2944](https://github.com/BurntSushi/ripgrep/pull/2944):\r\n  Fix a bug where the \"bytes searched\" in `--stats` output could be incorrect.\r\n* [BUG #2990](https://github.com/BurntSushi/ripgrep/issues/2990):\r\n  Fix a bug where ripgrep would mishandle globs that ended with a `.`.\r\n* [BUG #2094](https://github.com/BurntSushi/ripgrep/issues/2094),\r\n  [BUG #3076](https://github.com/BurntSushi/ripgrep/issues/3076):\r\n  Fix bug with `-m/--max-count` and `-U/--multiline` showing too many matches.\r\n* [BUG #3100](https://github.com/BurntSushi/ripgrep/pull/3100):\r\n  Preserve line terminators when using `-r/--replace` flag.\r\n* [BUG #3108](https://github.com/BurntSushi/ripgrep/issues/3108):\r\n  Fix a bug where `-q --files-without-match` inverted the exit code.\r\n* [BUG #3131](https://github.com/BurntSushi/ripgrep/issues/3131):\r\n  Document inconsistency between `-c/--count` and `--files-with-matches`.\r\n* [BUG #3135](https://github.com/BurntSushi/ripgrep/issues/3135):\r\n  Fix rare panic for some classes of large regexes on large haystacks.\r\n* [BUG #3140](https://github.com/BurntSushi/ripgrep/issues/3140):\r\n  Ensure hyphens in flag names are escaped in the roff text for the man page.\r\n* [BUG #3155](https://github.com/BurntSushi/ripgrep/issues/3155):\r\n  Statically compile PCRE2 into macOS release artifacts on `aarch64`.\r\n* [BUG #3173](https://github.com/BurntSushi/ripgrep/issues/3173):\r\n  Fix ancestor ignore filter bug when searching whitelisted hidden files.\r\n* [BUG #3178](https://github.com/BurntSushi/ripgrep/discussions/3178):\r\n  Fix bug causing incorrect summary statistics with `--json` flag.\r\n* [BUG #3179](https://github.com/BurntSushi/ripgrep/issues/3179):\r\n  Fix gitignore bug when searching absolute paths with global gitignores.\r\n* [BUG #3180](https://github.com/BurntSushi/ripgrep/issues/3180):\r\n  Fix a panicking bug when using `-U/--multiline` and `-r/--replace`.\r\n\r\nFeature enhancements:\r\n\r\n* Many enhancements to the default set of file types available for filtering.\r\n* [FEATURE #1872](https://github.com/BurntSushi/ripgrep/issues/1872):\r\n  Make `-r/--replace` work with `--json`.\r\n* [FEATURE #2708](https://github.com/BurntSushi/ripgrep/pull/2708):\r\n  Completions for the fish shell take ripgrep's config file into account.\r\n* [FEATURE #2841](https://github.com/BurntSushi/ripgrep/pull/2841):\r\n  Add `italic` to the list of available style attributes in `--color`.\r\n* [FEATURE #2842](https://github.com/BurntSushi/ripgrep/pull/2842):\r\n  Directories containing `.jj` are now treated as git repositories.\r\n* [FEATURE #2849](https://github.com/BurntSushi/ripgrep/pull/2849):\r\n  When using multithreading, schedule files to search in order given on CLI.\r\n* [FEATURE #2943](https://github.com/BurntSushi/ripgrep/issues/2943):\r\n  Add `aarch64` release artifacts for Windows.\r\n* [FEATURE #3024](https://github.com/BurntSushi/ripgrep/issues/3024):\r\n  Add `highlight` color type, for styling non-matching text in a matching line.\r\n* [FEATURE #3048](https://github.com/BurntSushi/ripgrep/pull/3048):\r\n  Globs in ripgrep (and the `globset` crate) now support nested alternates.\r\n* [FEATURE #3096](https://github.com/BurntSushi/ripgrep/pull/3096):\r\n  Improve completions for `--hyperlink-format` in bash and fish.\r\n* [FEATURE #3102](https://github.com/BurntSushi/ripgrep/pull/3102):\r\n  Improve completions for `--hyperlink-format` in zsh.",
  "reactions": {
    "url": "https://api.github.com/repos/BurntSushi/ripgrep/releases/254873528/reactions",
    "total_count": 246,
    "+1": 111,
    "-1": 0,
    "laugh": 6,
    "hooray": 47,
    "confused": 0,
    "heart": 45,
    "rocket": 33,
    "eyes": 4
  }
}
